nonebot/adapters/qq/__init__.py
nonebot/adapters/qq/adapter.py
nonebot/adapters/qq/bot.py
nonebot/adapters/qq/compat.py
nonebot/adapters/qq/config.py
nonebot/adapters/qq/event.py
nonebot/adapters/qq/exception.py
nonebot/adapters/qq/message.py
nonebot/adapters/qq/models/__init__.py
nonebot/adapters/qq/models/common.py
nonebot/adapters/qq/models/guild.py
nonebot/adapters/qq/models/payload.py
nonebot/adapters/qq/models/qq.py
nonebot/adapters/qq/permission.py
nonebot/adapters/qq/store.py
nonebot/adapters/qq/utils.py
nonebot_adapter_qq-1.6.4.dist-info/LICENSE
nonebot_adapter_qq-1.6.4.dist-info/METADATA
nonebot_adapter_qq-1.6.4.dist-info/WHEEL
nonebot_adapter_qq-1.6.4.dist-info/RECORD
