Metadata-Version: 2.3
Name: nonebot-adapter-qq
Version: 1.6.4
Summary: QQ adapter for nonebot2
License: MIT
Keywords: bot,qq,qqbot,qqguild
Author: yanyongyu
Author-email: yyy@nonebot.dev
Requires-Python: >=3.9,<4.0
Classifier: Development Status :: 5 - Production/Stable
Classifier: Framework :: Robot Framework
Classifier: Framework :: Robot Framework :: Library
Classifier: License :: OSI Approved :: MIT License
Classifier: Operating System :: OS Independent
Classifier: Programming Language :: Python :: 3
Classifier: Programming Language :: Python :: 3.9
Classifier: Programming Language :: Python :: 3.10
Classifier: Programming Language :: Python :: 3.11
Classifier: Programming Language :: Python :: 3.12
Classifier: Programming Language :: Python :: 3.13
Requires-Dist: cryptography (>=43.0.3,<45.0.0)
Requires-Dist: nonebot2 (>=2.2.1,<3.0.0)
Requires-Dist: pydantic (>=1.10.0,<3.0.0,!=2.5.0,!=2.5.1)
Requires-Dist: typing-extensions (>=4.4.0,<5.0.0)
Requires-Dist: yarl (>=1.9.0,<2.0.0)
Project-URL: Documentation, https://github.com/nonebot/adapter-qq#readme
Project-URL: Homepage, https://github.com/nonebot/adapter-qq
Project-URL: Repository, https://github.com/nonebot/adapter-qq
